<?xml version="1.0" encoding="utf-8" ?><DRUID><Rotation><RotationName>KittyCleave</RotationName><RotationDefault>false</RotationDefault><RotationList>Ravage|Faerie Fire (Feral)|Tigers Fury|Ferocious Bite|Rip|Mangle|Rake|Savage Roar|Shred</RotationList><RequireCombat>true</RequireCombat><RotationNotes></RotationNotes></Rotation><Rotation><RotationName>KittyAoE</RotationName><RotationDefault>false</RotationDefault><RotationList>Swipe|Tigers Fury</RotationList><RequireCombat>true</RequireCombat><RotationNotes></RotationNotes></Rotation><Rotation><RotationName>BerserkAoE</RotationName><RotationDefault>false</RotationDefault><RotationList>Swipe|Tigers Fury|Berserk</RotationList><RequireCombat>true</RequireCombat><RotationNotes></RotationNotes></Rotation><Rotation><RotationName>Resto</RotationName><RotationDefault>false</RotationDefault><RotationList>Resto: Autotarget LowHP|Resto: Tranquility|Resto: Swiftmend|Resto: Innervate|Resto: Rejuvenation|Resto: Regrowth|Resto: Healing Touch|Resto: Wild Growth|Resto: Nourish|Resto: Lifebloom</RotationList><RequireCombat>false</RequireCombat><RotationNotes>Focus the tank to keep the 3 staks of Lifebloom</RotationNotes></Rotation><Rotation><RotationName>Bloomish</RotationName><RotationDefault>false</RotationDefault><RotationList>Resto: Lifebloom|Resto: Innervate</RotationList><RequireCombat>true</RequireCombat><RotationNotes></RotationNotes></Rotation></DRUID>